calm_cache
