Metadata-Version: 1.1
Name: django-calm-cache
Version: 0.9.2
Summary: A set of useful tools that enhance the standard Django cache experience
Home-page: https://bitbucket.org/pitcrews/django-calm-cache
Author: Fairfax Media
Author-email: opensource@pitcre.ws
License: BSD 3-Clause
Keywords: django cache memcache memcached minting pylibmc libmemcached
Platform: Platform Independent
Classifier: Development Status :: 4 - Beta
Classifier: Environment :: Web Environment
Classifier: Framework :: Django
Classifier: Intended Audience :: Developers
Classifier: License :: OSI Approved :: BSD License
Classifier: Topic :: Internet :: WWW/HTTP
Classifier: Topic :: Internet :: WWW/HTTP :: Dynamic Content
Classifier: Topic :: Software Development :: Libraries :: Python Modules
Classifier: Operating System :: OS Independent
Classifier: Programming Language :: Python
Classifier: Programming Language :: Python :: 2.7
Classifier: Programming Language :: Python :: 3.3
